[
    {
        "type": "info",
        "seed": 2550581636,
        "countVertex": 10,
        "density": 3,
        "size": 1
    },
    {
        "type": "startPoint",
        "x": 2.0,
        "y": 2.0
    },
    {
        "type": "endPoint",
        "x": 98.0,
        "y": 98.0
    },
    {
        "type": "polygon",
        "points": [
            {
                "type": "point",
                "x": 71.07676514502006,
                "y": 6.2365585401194235
            },
            {
                "type": "point",
                "x": 71.3040740886083,
                "y": 5.555362533333314
            },
            {
                "type": "point",
                "x": 70.76792669417492,
                "y": 4.721210563695923
            },
            {
                "type": "point",
                "x": 69.83190997813196,
                "y": 5.220779522577008
            },
            {
                "type": "point",
                "x": 69.91236096332244,
                "y": 5.983807792912891
            }
        ]
    },
    {
        "type": "polygon",
        "points": [
            {
                "type": "point",
                "x": 56.180145002591026,
                "y": 11.616922088671929
            },
            {
                "type": "point",
                "x": 56.23381330167996,
                "y": 10.920120506951129
            },
            {
                "type": "point",
                "x": 55.56753994186442,
                "y": 10.82222860602382
            },
            {
                "type": "point",
                "x": 55.06364356145538,
                "y": 10.648599729889632
            },
            {
                "type": "point",
                "x": 54.704510757083526,
                "y": 11.362249605818683
            },
            {
                "type": "point",
                "x": 54.71547955878832,
                "y": 12.03063163114821
            },
            {
                "type": "point",
                "x": 55.09985274251068,
                "y": 12.22733121120915
            },
            {
                "type": "point",
                "x": 55.73600975166347,
                "y": 12.194077961006219
            }
        ]
    },
    {
        "type": "polygon",
        "points": [
            {
                "type": "point",
                "x": 25.67097603297036,
                "y": 16.092527775983218
            },
            {
                "type": "point",
                "x": 26.123883829443734,
                "y": 15.587760300693017
            },
            {
                "type": "point",
                "x": 26.3846631582738,
                "y": 15.39033683739865
            },
            {
                "type": "point",
                "x": 26.316633116898263,
                "y": 14.810386062415148
            },
            {
                "type": "point",
                "x": 25.94084845588822,
                "y": 14.299938789541207
            },
            {
                "type": "point",
                "x": 25.50238831591133,
                "y": 14.361235771607722
            },
            {
                "type": "point",
                "x": 25.067654928480255,
                "y": 14.478068230239026
            },
            {
                "type": "point",
                "x": 24.830126381514816,
                "y": 15.142008868916074
            },
            {
                "type": "point",
                "x": 24.90444724248128,
                "y": 15.499910582020885
            },
            {
                "type": "point",
                "x": 25.162263464360898,
                "y": 15.872257252570279
            }
        ]
    },
    {
        "type": "polygon",
        "points": [
            {
                "type": "point",
                "x": 57.18930512131346,
                "y": 55.84592219933655
            },
            {
                "type": "point",
                "x": 57.593551763102006,
                "y": 54.73721459969755
            },
            {
                "type": "point",
                "x": 56.43052474757423,
                "y": 54.783596219375255
            }
        ]
    },
    {
        "type": "polygon",
        "points": [
            {
                "type": "point",
                "x": 84.07363030108175,
                "y": 60.287871718031255
            },
            {
                "type": "point",
                "x": 83.93436874635591,
                "y": 61.40142950751285
            },
            {
                "type": "point",
                "x": 85.49969498728176,
                "y": 60.663425433128
            }
        ]
    },
    {
        "type": "polygon",
        "points": [
            {
                "type": "point",
                "x": 31.28620642473131,
                "y": 63.46149856099597
            },
            {
                "type": "point",
                "x": 32.177996010883106,
                "y": 63.159001770451475
            },
            {
                "type": "point",
                "x": 31.640433986876303,
                "y": 61.9799670943047
            },
            {
                "type": "point",
                "x": 30.656557911819018,
                "y": 62.480566055223925
            }
        ]
    },
    {
        "type": "polygon",
        "points": [
            {
                "type": "point",
                "x": 75.96243514911099,
                "y": 92.57055608585867
            },
            {
                "type": "point",
                "x": 76.55711205442445,
                "y": 92.68500662352557
            },
            {
                "type": "point",
                "x": 76.8948595389359,
                "y": 92.25744240455917
            },
            {
                "type": "point",
                "x": 77.02878457007853,
                "y": 91.80582585563965
            },
            {
                "type": "point",
                "x": 77.03571064560381,
                "y": 91.24295254586697
            },
            {
                "type": "point",
                "x": 76.31663281712534,
                "y": 90.98883665747395
            },
            {
                "type": "point",
                "x": 75.8920634300699,
                "y": 91.32129954336494
            },
            {
                "type": "point",
                "x": 75.487079523699,
                "y": 91.74255116122158
            },
            {
                "type": "point",
                "x": 75.56910273967043,
                "y": 92.34289879046041
            }
        ]
    },
    {
        "type": "polygon",
        "points": [
            {
                "type": "point",
                "x": 8.686447720037803,
                "y": 93.02338515985491
            },
            {
                "type": "point",
                "x": 7.915454138325559,
                "y": 93.25371744361475
            },
            {
                "type": "point",
                "x": 7.6859890728676215,
                "y": 93.60750000664477
            },
            {
                "type": "point",
                "x": 7.867938179252118,
                "y": 94.12134256324897
            },
            {
                "type": "point",
                "x": 8.032794576101528,
                "y": 94.72118799898868
            },
            {
                "type": "point",
                "x": 8.692270032237108,
                "y": 94.58389007665023
            },
            {
                "type": "point",
                "x": 9.221314245430168,
                "y": 94.49058921908517
            },
            {
                "type": "point",
                "x": 9.359690913727986,
                "y": 93.72329735726653
            },
            {
                "type": "point",
                "x": 9.238881954637886,
                "y": 93.19663078825063
            }
        ]
    },
    {
        "type": "polygon",
        "points": [
            {
                "type": "point",
                "x": 45.63612448958083,
                "y": 97.53540881024684
            },
            {
                "type": "point",
                "x": 45.28811616912621,
                "y": 98.17906174524902
            },
            {
                "type": "point",
                "x": 46.02536671582344,
                "y": 99.10086291954347
            },
            {
                "type": "point",
                "x": 46.53434567204697,
                "y": 99.07386637907794
            },
            {
                "type": "point",
                "x": 47.19035988968105,
                "y": 98.46925436729465
            },
            {
                "type": "point",
                "x": 46.5616080115616,
                "y": 97.68977148622115
            }
        ]
    }
]